xdas/__init__.py
xdas/config.py
xdas/fft.py
xdas/parallel.py
xdas/signal.py
xdas/spectral.py
xdas/synthetics.py
xdas/trigger.py
xdas/virtual.py
xdas/atoms/__init__.py
xdas/atoms/core.py
xdas/atoms/ml.py
xdas/atoms/signal.py
xdas/core/__init__.py
xdas/core/coordinates.py
xdas/core/dataarray.py
xdas/core/datacollection.py
xdas/core/methods.py
xdas/core/numpy.py
xdas/core/routines.py
xdas/dask/__init__.py
xdas/dask/core.py
xdas/dask/serial.py
xdas/io/__init__.py
xdas/io/apsensing.py
xdas/io/asn.py
xdas/io/core.py
xdas/io/febus.py
xdas/io/miniseed.py
xdas/io/optasense.py
xdas/io/silixa.py
xdas/io/sintela.py
xdas/io/tdms.py
xdas/io/terra15.py
xdas/processing/__init__.py
xdas/processing/core.py
xdas/processing/monitor.py
xdas-0.2.3.dist-info/licenses/LICENSE.md
xdas-0.2.3.dist-info/METADATA
xdas-0.2.3.dist-info/WHEEL
xdas-0.2.3.dist-info/top_level.txt
xdas-0.2.3.dist-info/RECORD
