Metadata-Version: 2.4
Name: xdas
Version: 0.2.3
Author-email: Alister Trabattoni <alister.trabattoni@gmail.com>
Requires-Python: >=3.10
License-File: LICENSE.md
Requires-Dist: dask<2025.4.0
Requires-Dist: h5netcdf
Requires-Dist: h5py
Requires-Dist: hdf5plugin
Requires-Dist: msgpack
Requires-Dist: numba
Requires-Dist: numpy
Requires-Dist: obspy
Requires-Dist: pandas
Requires-Dist: plotly
Requires-Dist: scipy
Requires-Dist: tqdm
Requires-Dist: watchdog
Requires-Dist: xarray
Requires-Dist: xinterp
Requires-Dist: pyzmq
Provides-Extra: dev
Requires-Dist: black; extra == "dev"
Requires-Dist: build; extra == "dev"
Requires-Dist: isort; extra == "dev"
Requires-Dist: twine; extra == "dev"
Provides-Extra: docs
Requires-Dist: ipykernel; extra == "docs"
Requires-Dist: matplotlib; extra == "docs"
Requires-Dist: myst-nb; extra == "docs"
Requires-Dist: pydata-sphinx-theme; extra == "docs"
Requires-Dist: sphinx-design; extra == "docs"
Requires-Dist: sphinx-copybutton; extra == "docs"
Requires-Dist: sphinx; extra == "docs"
Provides-Extra: tests
Requires-Dist: pytest; extra == "tests"
Requires-Dist: pytest-cov; extra == "tests"
Requires-Dist: seisbench; extra == "tests"
Requires-Dist: torch; extra == "tests"
Dynamic: license-file
